tiptree/__init__.py
tiptree/client.py
tiptree/exceptions.py
tiptree/interface_models.py
tiptree/run.py
tiptree/utils.py
tiptree/mixins/__init__.py
tiptree/mixins/agent.py
tiptree/mixins/agent_session.py
tiptree/mixins/message.py
tiptree-0.0.4.dist-info/METADATA
tiptree-0.0.4.dist-info/WHEEL
tiptree-0.0.4.dist-info/entry_points.txt
tiptree-0.0.4.dist-info/licenses/LICENSE
tiptree-0.0.4.dist-info/RECORD
