Metadata-Version: 2.4
Name: tiptree
Version: 0.0.4
Summary: Client library for the Tiptree Platform API
Project-URL: Homepage, https://github.com/tiptreesystems/tiptree-clients
Project-URL: Bug Tracker, https://github.com/tiptreesystems/tiptree-clients/issues
Author: Tiptree Advanced Systems Corporation
License: MIT License
License-File: LICENSE
Classifier: Development Status :: 4 - Beta
Classifier: Intended Audience :: Developers
Classifier: License :: OSI Approved :: MIT License
Classifier: Operating System :: OS Independent
Classifier: Programming Language :: Python :: 3
Classifier: Programming Language :: Python :: 3.9
Classifier: Programming Language :: Python :: 3.10
Classifier: Programming Language :: Python :: 3.11
Classifier: Topic :: Software Development :: Libraries :: Python Modules
Requires-Python: >=3.9
Requires-Dist: httpx>=0.24.0
Requires-Dist: pydantic>=2.0.0
Requires-Dist: typing-extensions>=4.0.0
